iploka_geoip/__init__.py
iploka_geoip/exceptions.py
iploka_geoip/geoip.py
iploka_geoip/settings.py
iploka_python-1.0.0.dist-info/METADATA
iploka_python-1.0.0.dist-info/WHEEL
iploka_python-1.0.0.dist-info/top_level.txt
iploka_python-1.0.0.dist-info/RECORD
